torchcat/__init__.py
torchcat/cat.py
torchcat/datasets.py
torchcat/metrics.py
torchcat-0.1.5.dist-info/LICENSE
torchcat-0.1.5.dist-info/METADATA
torchcat-0.1.5.dist-info/WHEEL
torchcat-0.1.5.dist-info/top_level.txt
torchcat-0.1.5.dist-info/RECORD
