Metadata-Version: 2.1
Name: torchcat
Version: 0.1.5
Summary: TorchCat🐱 是用于封装 PyTorch 模型的工具
Home-page: https://gitee.com/kkkaiyu/torchcat
Author: KaiYu
Author-email: 2971934557@qq.com
License: GPLv3
Requires-Python: >=3.9
License-File: LICENSE
Requires-Dist: torchsummary
Requires-Dist: pandas
Requires-Dist: numpy
